confluence_as/__init__.py
confluence_as/adf_helper.py
confluence_as/autocomplete_cache.py
confluence_as/config_manager.py
confluence_as/confluence_client.py
confluence_as/credential_manager.py
confluence_as/error_handler.py
confluence_as/formatters.py
confluence_as/markdown_parser.py
confluence_as/space_context.py
confluence_as/validators.py
confluence_as/xhtml_helper.py
confluence_as/cli/__init__.py
confluence_as/cli/cli_utils.py
confluence_as/cli/helpers.py
confluence_as/cli/main.py
confluence_as/cli/commands/__init__.py
confluence_as/cli/commands/admin_cmds.py
confluence_as/cli/commands/analytics_cmds.py
confluence_as/cli/commands/attachment_cmds.py
confluence_as/cli/commands/bulk_cmds.py
confluence_as/cli/commands/comment_cmds.py
confluence_as/cli/commands/hierarchy_cmds.py
confluence_as/cli/commands/jira_cmds.py
confluence_as/cli/commands/label_cmds.py
confluence_as/cli/commands/ops_cmds.py
confluence_as/cli/commands/page_cmds.py
confluence_as/cli/commands/permission_cmds.py
confluence_as/cli/commands/property_cmds.py
confluence_as/cli/commands/search_cmds.py
confluence_as/cli/commands/space_cmds.py
confluence_as/cli/commands/template_cmds.py
confluence_as/cli/commands/watch_cmds.py
confluence_as/mock/__init__.py
confluence_as/mock/base.py
confluence_as/mock/client.py
confluence_as/mock/mixins/__init__.py
confluence_as/mock/mixins/content.py
confluence_as/mock/mixins/page.py
confluence_as/mock/mixins/space.py
confluence_as-1.1.0.dist-info/METADATA
confluence_as-1.1.0.dist-info/WHEEL
confluence_as-1.1.0.dist-info/entry_points.txt
confluence_as-1.1.0.dist-info/licenses/LICENSE
confluence_as-1.1.0.dist-info/RECORD
