Metadata-Version: 2.4
Name: confluence-as
Version: 1.1.0
Summary: Python library for Confluence Cloud REST API - shared utilities for Confluence automation
Project-URL: Homepage, https://github.com/grandcamel/confluence-as
Project-URL: Documentation, https://github.com/grandcamel/confluence-as#readme
Project-URL: Repository, https://github.com/grandcamel/confluence-as
Project-URL: Issues, https://github.com/grandcamel/confluence-as/issues
Project-URL: Changelog, https://github.com/grandcamel/confluence-as/blob/main/CHANGELOG.md
Author-email: grandcamel <noreply@github.com>
License-Expression: MIT
License-File: LICENSE
Keywords: api,atlassian,automation,cloud,confluence,documentation,rest
Classifier: Development Status :: 4 - Beta
Classifier: Intended Audience :: Developers
Classifier: License :: OSI Approved :: MIT License
Classifier: Operating System :: OS Independent
Classifier: Programming Language :: Python :: 3
Classifier: Programming Language :: Python :: 3.9
Classifier: Programming Language :: Python :: 3.10
Classifier: Programming Language :: Python :: 3.11
Classifier: Programming Language :: Python :: 3.12
Classifier: Programming Language :: Python :: 3.13
Classifier: Topic :: Documentation
Classifier: Topic :: Internet :: WWW/HTTP :: Dynamic Content
Classifier: Topic :: Software Development :: Libraries :: Python Modules
Requires-Python: >=3.9
Requires-Dist: assistant-skills-lib>=1.0.0
Requires-Dist: click>=8.0.0
Requires-Dist: requests>=2.28.0
Provides-Extra: dev
Requires-Dist: bandit>=1.7.0; extra == 'dev'
Requires-Dist: click>=8.0.0; extra == 'dev'
Requires-Dist: coverage>=7.0.0; extra == 'dev'
Requires-Dist: mypy>=1.8.0; extra == 'dev'
Requires-Dist: pre-commit>=3.0.0; extra == 'dev'
Requires-Dist: pytest-cov>=4.0.0; extra == 'dev'
Requires-Dist: pytest-mock>=3.10.0; extra == 'dev'
Requires-Dist: pytest>=7.0.0; extra == 'dev'
Requires-Dist: responses>=0.23.0; extra == 'dev'
Requires-Dist: ruff>=0.4.0; extra == 'dev'
Requires-Dist: types-requests>=2.28.0; extra == 'dev'
